readalongs/__init__.py
readalongs/_version.py
readalongs/align.py
readalongs/align_utils.py
readalongs/api.py
readalongs/audio_utils.py
readalongs/cli.py
readalongs/dna_utils.py
readalongs/log.py
readalongs/portable_tempfile.py
readalongs/util.py
readalongs/web_api.py
readalongs/epub/__init__.py
readalongs/epub/create_epub.py
readalongs/epub/templates/container.xml
readalongs/epub/templates/mimetype
readalongs/epub/templates/package.opf
readalongs/epub/templates/stylesheet.css
readalongs/static/read-along-1.0.dtd
readalongs/static/read-along-1.1.dtd
readalongs/static/read-along-1.2.dtd
readalongs/static/model/cmusphinx-en-us-5.2/README
readalongs/static/model/cmusphinx-en-us-5.2/feat_params.json
readalongs/static/model/cmusphinx-en-us-5.2/feature_transform
readalongs/static/model/cmusphinx-en-us-5.2/mdef
readalongs/static/model/cmusphinx-en-us-5.2/mdef.ci
readalongs/static/model/cmusphinx-en-us-5.2/means
readalongs/static/model/cmusphinx-en-us-5.2/mixture_weights
readalongs/static/model/cmusphinx-en-us-5.2/noisedict.txt
readalongs/static/model/cmusphinx-en-us-5.2/transition_matrices
readalongs/static/model/cmusphinx-en-us-5.2/variances
readalongs/text/README.md
readalongs/text/__init__.py
readalongs/text/add_elements_to_xml.py
readalongs/text/add_ids_to_xml.py
readalongs/text/bundle.css
readalongs/text/bundle.js
readalongs/text/convert_xml.py
readalongs/text/make_dict.py
readalongs/text/make_fsg.py
readalongs/text/make_package.py
readalongs/text/make_smil.py
readalongs/text/tokenize_xml.py
readalongs/text/util.py
readalongs/waveform2svg/__init__.py
readalongs/waveform2svg/audio_util.py
readalongs/waveform2svg/halfwav.svg
readalongs/waveform2svg/make_all_svgs.py
readalongs/waveform2svg/pitch.svg
readalongs/waveform2svg/pitch2svg.py
readalongs/waveform2svg/units.svg
readalongs/waveform2svg/units2svg.py
readalongs/waveform2svg/wav.svg
readalongs/waveform2svg/waveform2svg.py
readalongs-1.2.1.dist-info/METADATA
readalongs-1.2.1.dist-info/WHEEL
readalongs-1.2.1.dist-info/entry_points.txt
readalongs-1.2.1.dist-info/licenses/LICENSE
readalongs-1.2.1.dist-info/RECORD
