Metadata-Version: 2.4
Name: readalongs
Version: 1.2.1
Summary: ReadAlong Studio: Audiobook alignment for Indigenous languages
Project-URL: Homepage, https://github.com/ReadAlongs/
Project-URL: Documentation, https://readalongs.github.io/Studio/
Project-URL: Repository, https://github.com/ReadAlongs/Studio
Project-URL: Issues, https://github.com/ReadAlongs/Studio/issues
Project-URL: Changelog, https://github.com/ReadAlongs/Studio/releases
Author-email: Aidan Pine <Aidan.Pine@nrc-cnrc.gc.ca>, David Huggins-Daines <dhd@ecolingui.ca>, Eric Joanis <Eric.Joanis@nrc-cnrc.gc.ca>, Patrick Littell <Patrick.Littell@nrc-cnrc.gc.ca>, Delasie Torkornoo <Delasie.Torkornoo@nrc-cnrc.gc.ca>
Maintainer-email: Eric Joanis <Eric.Joanis@nrc-cnrc.gc.ca>, Aidan Pine <Aidan.Pine@nrc-cnrc.gc.ca>, David Huggins-Daines <dhd@ecolingui.ca>
License-File: LICENSE
Classifier: Intended Audience :: Education
Classifier: License :: OSI Approved :: MIT License
Classifier: Operating System :: OS Independent
Classifier: Programming Language :: Python :: 3
Classifier: Programming Language :: Python :: 3.8
Classifier: Programming Language :: Python :: 3.9
Classifier: Programming Language :: Python :: 3.10
Classifier: Programming Language :: Python :: 3.11
Classifier: Programming Language :: Python :: 3.12
Classifier: Programming Language :: Python :: 3.13
Classifier: Topic :: Multimedia :: Sound/Audio :: Speech
Classifier: Typing :: Typed
Requires-Python: >=3.8
Requires-Dist: audioop-lts; python_version >= '3.13'
Requires-Dist: chevron==0.14.0
Requires-Dist: click>=8.0.4
Requires-Dist: coloredlogs>=10.0
Requires-Dist: fastapi>=0.103.0
Requires-Dist: g2p<3,>=1.1.20230822
Requires-Dist: lxml>=4.9.4
Requires-Dist: numpy>=1.20.2
Requires-Dist: pydantic<3,>=1.8.2
Requires-Dist: pydub>=0.23.1
Requires-Dist: pympi-ling<2.0,>=1.69
Requires-Dist: python-slugify==5.0.0
Requires-Dist: requests>=2.31.0
Requires-Dist: soundswallower~=0.6.0
Requires-Dist: webvtt-py==0.4.2
Provides-Extra: all
Requires-Dist: coverage; extra == 'all'
Requires-Dist: gitlint-core>=0.17.0; extra == 'all'
Requires-Dist: gunicorn>=23.0.0; (platform_system != 'Windows') and extra == 'all'
Requires-Dist: httpx>=0.24.1; extra == 'all'
Requires-Dist: licensecheck; extra == 'all'
Requires-Dist: pep440>=0.1.2; extra == 'all'
Requires-Dist: pre-commit>=2.6.0; extra == 'all'
Requires-Dist: uvicorn>=0.30.1; extra == 'all'
Provides-Extra: api
Requires-Dist: gunicorn>=23.0.0; (platform_system != 'Windows') and extra == 'api'
Requires-Dist: uvicorn>=0.30.1; extra == 'api'
Provides-Extra: ci
Requires-Dist: coverage; extra == 'ci'
Requires-Dist: gunicorn>=23.0.0; (platform_system != 'Windows') and extra == 'ci'
Requires-Dist: licensecheck; extra == 'ci'
Requires-Dist: uvicorn>=0.30.1; extra == 'ci'
Provides-Extra: dev
Requires-Dist: gitlint-core>=0.17.0; extra == 'dev'
Requires-Dist: gunicorn>=23.0.0; (platform_system != 'Windows') and extra == 'dev'
Requires-Dist: httpx>=0.24.1; extra == 'dev'
Requires-Dist: pep440>=0.1.2; extra == 'dev'
Requires-Dist: pre-commit>=2.6.0; extra == 'dev'
Requires-Dist: uvicorn>=0.30.1; extra == 'dev'
